[{"id":"document","version":"1.0","clock":{"currentTime":"2024-07-07T08:26:41Z"}},{"id":"EOLE 44 LMT","label":{"text":"EOLE 44 LMT","scale":0.3,"pixelOffset":{"cartesian2":[0.0, -40.0]}},"model":{"gltf":"models/sailboat/1368Sailboat.gltf","scale":2.0,"heightReference":"RELATIVE_TO_GROUND"},"orientation":{"velocityReference":"#position"},"position":{"cartographicDegrees":["2024-07-07T08:26:41Z",-1.58484254272594,50.6802445761355,-60,"2024-07-07T08:27:21Z",-1.58426836366349,50.6814887681806,-60],"interpolationAlgorithm":"LINEAR","forwardExtrapolationType":"HOLD"}},{"id":"URKETA","label":{"text":"URKETA","scale":0.3,"pixelOffset":{"cartesian2":[0.0, -40.0]}},"model":{"gltf":"models/sailboat/1368Sailboat.gltf","scale":2.0,"heightReference":"RELATIVE_TO_GROUND"},"orientation":{"velocityReference":"#position"},"position":{"cartographicDegrees":["2024-07-07T08:26:41Z",-1.6880622586915,50.4211161414045,-60,"2024-07-07T08:27:21Z",-1.68747864609901,50.4226075218727,-60],"interpolationAlgorithm":"LINEAR","forwardExtrapolationType":"HOLD"}},{"id":"BONANZA59","label":{"text":"BONANZA59","scale":0.3,"pixelOffset":{"cartesian2":[0.0, -40.0]}},"model":{"gltf":"models/sailboat/1368Sailboat.gltf","scale":2.0,"heightReference":"RELATIVE_TO_GROUND"},"orientation":{"velocityReference":"#position"},"position":{"cartographicDegrees":["2024-07-07T08:26:41Z",-1.65744067492634,50.4976179689546,-60,"2024-07-07T08:27:21Z",-1.65675586397924,50.4990339586062,-60],"interpolationAlgorithm":"LINEAR","forwardExtrapolationType":"HOLD"}},{"id":"GUEST_1709322543322","label":{"text":"GUEST_1709322543322","scale":0.3,"pixelOffset":{"cartesian2":[0.0, -40.0]}},"model":{"gltf":"models/sailboat/1368Sailboat.gltf","scale":2.0,"heightReference":"RELATIVE_TO_GROUND"},"orientation":{"velocityReference":"#position"},"position":{"cartographicDegrees":["2024-07-07T08:26:41Z",-2.2867749705076,49.7548662828476,-60,"2024-07-07T08:27:21Z",-2.28546920474108,49.7567610437967,-60],"interpolationAlgorithm":"LINEAR","forwardExtrapolationType":"HOLD"}},{"id":"ARIE66","label":{"text":"ARIE66","scale":0.3,"pixelOffset":{"cartesian2":[0.0, -40.0]}},"model":{"gltf":"models/sailboat/1368Sailboat.gltf","scale":2.0,"heightReference":"RELATIVE_TO_GROUND"},"orientation":{"velocityReference":"#position"},"position":{"cartographicDegrees":["2024-07-07T08:26:41Z",-1.70168098948683,50.4695964883779,-60,"2024-07-07T08:27:21Z",-1.70083627991028,50.4708569845039,-60],"interpolationAlgorithm":"LINEAR","forwardExtrapolationType":"HOLD"}},{"id":"CAP-NANNE ESOG49","label":{"text":"CAP-NANNE ESOG49","scale":0.3,"pixelOffset":{"cartesian2":[0.0, -40.0]}},"model":{"gltf":"models/sailboat/1368Sailboat.gltf","scale":2.0,"heightReference":"RELATIVE_TO_GROUND"},"orientation":{"velocityReference":"#position"},"position":{"cartographicDegrees":["2024-07-07T08:26:41Z",-1.63529346113332,50.5203457840701,-60,"2024-07-07T08:27:21Z",-1.63484558882566,50.5219127120935,-60],"interpolationAlgorithm":"LINEAR","forwardExtrapolationType":"HOLD"}},{"id":"NICO_JUD - PVE","label":{"text":"NICO_JUD - PVE","scale":0.3,"pixelOffset":{"cartesian2":[0.0, -40.0]}},"model":{"gltf":"models/sailboat/1368Sailboat.gltf","scale":2.0,"heightReference":"RELATIVE_TO_GROUND"},"orientation":{"velocityReference":"#position"},"position":{"cartographicDegrees":["2024-07-07T08:26:41Z",-1.58730267942882,50.6757869606773,-60,"2024-07-07T08:27:21Z",-1.58671687835843,50.6770482809031,-60],"interpolationAlgorithm":"LINEAR","forwardExtrapolationType":"HOLD"}},{"id":"AR VAG >^;^","label":{"text":"AR VAG >^;^","scale":0.3,"pixelOffset":{"cartesian2":[0.0, -40.0]}},"model":{"gltf":"models/sailboat/1368Sailboat.gltf","scale":2.0,"heightReference":"RELATIVE_TO_GROUND"},"orientation":{"velocityReference":"#position"},"position":{"cartographicDegrees":["2024-07-07T08:26:41Z",-1.57984447577511,50.6774846092718,-60,"2024-07-07T08:27:21Z",-1.57853029953716,50.6775151456957,-60],"interpolationAlgorithm":"LINEAR","forwardExtrapolationType":"HOLD"}},{"id":"TEMERUS - PVE","label":{"text":"TEMERUS - PVE","scale":0.3,"pixelOffset":{"cartesian2":[0.0, -40.0]}},"model":{"gltf":"models/sailboat/1368Sailboat.gltf","scale":2.0,"heightReference":"RELATIVE_TO_GROUND"},"orientation":{"velocityReference":"#position"},"position":{"cartographicDegrees":["2024-07-07T08:26:41Z",-1.59480655222315,50.6573208415512,-60,"2024-07-07T08:27:21Z",-1.59440438194309,50.6587237887349,-60],"interpolationAlgorithm":"LINEAR","forwardExtrapolationType":"HOLD"}},{"id":"DANYMAILL _LPDB","label":{"text":"DANYMAILL _LPDB","scale":0.3,"pixelOffset":{"cartesian2":[0.0, -40.0]}},"model":{"gltf":"models/sailboat/1368Sailboat.gltf","scale":2.0,"heightReference":"RELATIVE_TO_GROUND"},"orientation":{"velocityReference":"#position"},"position":{"cartographicDegrees":["2024-07-07T08:26:41Z",-1.59527662790263,50.6652566119326,-60,"2024-07-07T08:27:21Z",-1.5945254729218,50.6663621492435,-60],"interpolationAlgorithm":"LINEAR","forwardExtrapolationType":"HOLD"}},{"id":"FRED28","label":{"text":"FRED28","scale":0.3,"pixelOffset":{"cartesian2":[0.0, -40.0]}},"model":{"gltf":"models/sailboat/1368Sailboat.gltf","scale":2.0,"heightReference":"RELATIVE_TO_GROUND"},"orientation":{"velocityReference":"#position"},"position":{"cartographicDegrees":["2024-07-07T08:26:41Z",-2.05365611688316,50.1499909534533,-60,"2024-07-07T08:27:21Z",-2.05253876948347,50.1512879379378,-60],"interpolationAlgorithm":"LINEAR","forwardExtrapolationType":"HOLD"}},{"id":"CRUNCH50","label":{"text":"CRUNCH50","scale":0.3,"pixelOffset":{"cartesian2":[0.0, -40.0]}},"model":{"gltf":"models/sailboat/1368Sailboat.gltf","scale":2.0,"heightReference":"RELATIVE_TO_GROUND"},"orientation":{"velocityReference":"#position"},"position":{"cartographicDegrees":["2024-07-07T08:26:41Z",-2.04348907603422,50.288416345572,-60,"2024-07-07T08:27:21Z",-2.04340309640548,50.2899894607627,-60],"interpolationAlgorithm":"LINEAR","forwardExtrapolationType":"HOLD"}},{"id":"HUBINATOR TG II FCKP","label":{"text":"HUBINATOR TG II FCKP","scale":0.3,"pixelOffset":{"cartesian2":[0.0, -40.0]}},"model":{"gltf":"models/sailboat/1368Sailboat.gltf","scale":2.0,"heightReference":"RELATIVE_TO_GROUND"},"orientation":{"velocityReference":"#position"},"position":{"cartographicDegrees":["2024-07-07T08:26:41Z",-1.58506588093964,50.6823634539504,-60,"2024-07-07T08:27:21Z",-1.58452181551066,50.6836322719339,-60],"interpolationAlgorithm":"LINEAR","forwardExtrapolationType":"HOLD"}},{"id":"SANDOKAN-EZ THESEACL","label":{"text":"SANDOKAN-EZ THESEACL","scale":0.3,"pixelOffset":{"cartesian2":[0.0, -40.0]}},"model":{"gltf":"models/sailboat/1368Sailboat.gltf","scale":2.0,"heightReference":"RELATIVE_TO_GROUND"},"orientation":{"velocityReference":"#position"},"position":{"cartographicDegrees":["2024-07-07T08:26:41Z",-1.58342599549563,50.6835243633773,-60,"2024-07-07T08:27:21Z",-1.58285863430959,50.6847698178364,-60],"interpolationAlgorithm":"LINEAR","forwardExtrapolationType":"HOLD"}},{"id":"ARISTO","label":{"text":"ARISTO","scale":0.3,"pixelOffset":{"cartesian2":[0.0, -40.0]}},"model":{"gltf":"models/sailboat/1368Sailboat.gltf","scale":2.0,"heightReference":"RELATIVE_TO_GROUND"},"orientation":{"velocityReference":"#position"},"position":{"cartographicDegrees":["2024-07-07T08:26:41Z",-1.89395674884335,50.2395707152064,-60,"2024-07-07T08:27:21Z",-1.89308562315229,50.2408832869419,-60],"interpolationAlgorithm":"LINEAR","forwardExtrapolationType":"HOLD"}},{"id":"SERIAL LOUZEUR","label":{"text":"SERIAL LOUZEUR","scale":0.3,"pixelOffset":{"cartesian2":[0.0, -40.0]}},"model":{"gltf":"models/sailboat/1368Sailboat.gltf","scale":2.0,"heightReference":"RELATIVE_TO_GROUND"},"orientation":{"velocityReference":"#position"},"position":{"cartographicDegrees":["2024-07-07T08:26:41Z",-2.32226826879678,49.8606430322675,-60,"2024-07-07T08:27:21Z",-2.32095860962398,49.8623740430233,-60],"interpolationAlgorithm":"LINEAR","forwardExtrapolationType":"HOLD"}},{"id":"MARAUD ELIOT","label":{"text":"MARAUD ELIOT","scale":0.3,"pixelOffset":{"cartesian2":[0.0, -40.0]}},"model":{"gltf":"models/sailboat/1368Sailboat.gltf","scale":2.0,"heightReference":"RELATIVE_TO_GROUND"},"orientation":{"velocityReference":"#position"},"position":{"cartographicDegrees":["2024-07-07T08:26:41Z",-1.85598691313893,50.3267344601883,-60,"2024-07-07T08:27:21Z",-1.85501351083414,50.3278509469177,-60],"interpolationAlgorithm":"LINEAR","forwardExtrapolationType":"HOLD"}},{"id":"THUR09 LMT","label":{"text":"THUR09 LMT","scale":0.3,"pixelOffset":{"cartesian2":[0.0, -40.0]}},"model":{"gltf":"models/sailboat/1368Sailboat.gltf","scale":2.0,"heightReference":"RELATIVE_TO_GROUND"},"orientation":{"velocityReference":"#position"},"position":{"cartographicDegrees":["2024-07-07T08:26:41Z",-1.65887277065285,50.5632813568487,-60,"2024-07-07T08:27:21Z",-1.65805765580112,50.5645501424649,-60],"interpolationAlgorithm":"LINEAR","forwardExtrapolationType":"HOLD"}},{"id":"CREVISSE-974","label":{"text":"CREVISSE-974","scale":0.3,"pixelOffset":{"cartesian2":[0.0, -40.0]}},"model":{"gltf":"models/sailboat/1368Sailboat.gltf","scale":2.0,"heightReference":"RELATIVE_TO_GROUND"},"orientation":{"velocityReference":"#position"},"position":{"cartographicDegrees":["2024-07-07T08:26:41Z",-1.64499109503186,50.5946525302829,-60,"2024-07-07T08:27:21Z",-1.64412808901832,50.5958273737105,-60],"interpolationAlgorithm":"LINEAR","forwardExtrapolationType":"HOLD"}},{"id":"ACCRO_JOGY","label":{"text":"ACCRO_JOGY","scale":0.3,"pixelOffset":{"cartesian2":[0.0, -40.0]}},"model":{"gltf":"models/sailboat/1368Sailboat.gltf","scale":2.0,"heightReference":"RELATIVE_TO_GROUND"},"orientation":{"velocityReference":"#position"},"position":{"cartographicDegrees":["2024-07-07T08:26:41Z",-2.08908608761143,49.8471473923011,-60,"2024-07-07T08:27:21Z",-2.09023478375073,49.8471538564015,-60],"interpolationAlgorithm":"LINEAR","forwardExtrapolationType":"HOLD"}},{"id":"AL452","label":{"text":"AL452","scale":0.3,"pixelOffset":{"cartesian2":[0.0, -40.0]}},"model":{"gltf":"models/sailboat/1368Sailboat.gltf","scale":2.0,"heightReference":"RELATIVE_TO_GROUND"},"orientation":{"velocityReference":"#position"},"position":{"cartographicDegrees":["2024-07-07T08:26:41Z",-2.05363440325165,49.995410917041,-60,"2024-07-07T08:27:21Z",-2.05252680371915,49.9970802227213,-60],"interpolationAlgorithm":"LINEAR","forwardExtrapolationType":"HOLD"}},{"id":"FLOCYCLO","label":{"text":"FLOCYCLO","scale":0.3,"pixelOffset":{"cartesian2":[0.0, -40.0]}},"model":{"gltf":"models/sailboat/1368Sailboat.gltf","scale":2.0,"heightReference":"RELATIVE_TO_GROUND"},"orientation":{"velocityReference":"#position"},"position":{"cartographicDegrees":["2024-07-07T08:26:41Z",-1.83992426945809,50.3968135289099,-60,"2024-07-07T08:27:21Z",-1.83898065481147,50.3978987052132,-60],"interpolationAlgorithm":"LINEAR","forwardExtrapolationType":"HOLD"}},{"id":"ONE WORLD","label":{"text":"ONE WORLD","scale":0.3,"pixelOffset":{"cartesian2":[0.0, -40.0]}},"model":{"gltf":"models/sailboat/1368Sailboat.gltf","scale":2.0,"heightReference":"RELATIVE_TO_GROUND"},"orientation":{"velocityReference":"#position"},"position":{"cartographicDegrees":["2024-07-07T08:26:41Z",-1.60288039030013,50.6362449001253,-60,"2024-07-07T08:27:21Z",-1.60243216375021,50.6376422001671,-60],"interpolationAlgorithm":"LINEAR","forwardExtrapolationType":"HOLD"}},{"id":"TIPAPACHERI BSP","label":{"text":"TIPAPACHERI BSP","scale":0.3,"pixelOffset":{"cartesian2":[0.0, -40.0]}},"model":{"gltf":"models/sailboat/1368Sailboat.gltf","scale":2.0,"heightReference":"RELATIVE_TO_GROUND"},"orientation":{"velocityReference":"#position"},"position":{"cartographicDegrees":["2024-07-07T08:26:41Z",-1.58662126266481,50.6796717033052,-60,"2024-07-07T08:27:21Z",-1.58607665740033,50.6809596044069,-60],"interpolationAlgorithm":"LINEAR","forwardExtrapolationType":"HOLD"}},{"id":"russor","label":{"text":"russor","scale":0.3,"pixelOffset":{"cartesian2":[0.0, -40.0]}},"model":{"gltf":"models/santa_isadora/scene.gltf","scale":2.0,"heightReference":"RELATIVE_TO_GROUND"},"orientation":{"velocityReference":"#position"},"position":{"cartographicDegrees":["2024-07-07T08:26:41Z",-2.15104191711084,49.7040422811145,-60,"2024-07-07T08:27:21Z",-2.15150899173793,49.7028556637082,-60],"interpolationAlgorithm":"LINEAR","forwardExtrapolationType":"HOLD"}}]