[{"id":"document","version":"1.0","clock":{"currentTime":"2024-07-08T17:08:51Z"}},{"id":"FRIGATE","label":{"text":"FRIGATE","scale":0.3,"pixelOffset":{"cartesian2":[0.0, -40.0]}},"model":{"gltf":"models/frigate/scene.gltf","scale":2.0,"heightReference":"RELATIVE_TO_GROUND"},"orientation":{"velocityReference":"#position"},"position":{"cartographicDegrees":["2024-07-08T17:08:51Z",-1.40268050214204,50.7551779807468,-6,"2024-07-08T17:09:31Z",-1.40234422996118,50.755242210035,-6],"interpolationAlgorithm":"LINEAR","forwardExtrapolationType":"HOLD"}},{"id":"NIKOPOL0386","label":{"text":"NIKOPOL0386","scale":0.3,"pixelOffset":{"cartesian2":[0.0, -40.0]}},"model":{"gltf":"models/sailboat/1368Sailboat.gltf","scale":1.0,"heightReference":"RELATIVE_TO_GROUND"},"orientation":{"velocityReference":"#position"},"position":{"cartographicDegrees":["2024-07-08T17:08:51Z",-0.222410269890732,50.0291374398466,-10,"2024-07-08T17:09:31Z",-0.221808841940394,50.0280759352194,-10],"interpolationAlgorithm":"LINEAR","forwardExtrapolationType":"HOLD"}},{"id":"GUEST_1714411924302","label":{"text":"GUEST_1714411924302","scale":0.3,"pixelOffset":{"cartesian2":[0.0, -40.0]}},"model":{"gltf":"models/sailboat/1368Sailboat.gltf","scale":1.0,"heightReference":"RELATIVE_TO_GROUND"},"orientation":{"velocityReference":"#position"},"position":{"cartographicDegrees":["2024-07-08T17:08:51Z",-0.692602365746388,50.367200745519,-10,"2024-07-08T17:09:31Z",-0.69216604043118,50.3666986490205,-10],"interpolationAlgorithm":"LINEAR","forwardExtrapolationType":"HOLD"}},{"id":"MAINIAC","label":{"text":"MAINIAC","scale":0.3,"pixelOffset":{"cartesian2":[0.0, -40.0]}},"model":{"gltf":"models/sailboat/1368Sailboat.gltf","scale":1.0,"heightReference":"RELATIVE_TO_GROUND"},"orientation":{"velocityReference":"#position"},"position":{"cartographicDegrees":["2024-07-08T17:08:51Z",-1.140725,50.749082,-10,"2024-07-08T17:09:31Z",-1.140725,50.749082,-10],"interpolationAlgorithm":"LINEAR","forwardExtrapolationType":"HOLD"}},{"id":"SDORFMEISTER","label":{"text":"SDORFMEISTER","scale":0.3,"pixelOffset":{"cartesian2":[0.0, -40.0]}},"model":{"gltf":"models/sailboat/1368Sailboat.gltf","scale":1.0,"heightReference":"RELATIVE_TO_GROUND"},"orientation":{"velocityReference":"#position"},"position":{"cartographicDegrees":["2024-07-08T17:08:51Z",0.129617,49.49022,-10,"2024-07-08T17:09:31Z",0.129617,49.49022,-10],"interpolationAlgorithm":"LINEAR","forwardExtrapolationType":"HOLD"}},{"id":"BENJITV08 - LPDB","label":{"text":"BENJITV08 - LPDB","scale":0.3,"pixelOffset":{"cartesian2":[0.0, -40.0]}},"model":{"gltf":"models/sailboat/1368Sailboat.gltf","scale":1.0,"heightReference":"RELATIVE_TO_GROUND"},"orientation":{"velocityReference":"#position"},"position":{"cartographicDegrees":["2024-07-08T17:08:51Z",0.129617,49.49022,-10,"2024-07-08T17:09:31Z",0.129617,49.49022,-10],"interpolationAlgorithm":"LINEAR","forwardExtrapolationType":"HOLD"}},{"id":"PALILULA","label":{"text":"PALILULA","scale":0.3,"pixelOffset":{"cartesian2":[0.0, -40.0]}},"model":{"gltf":"models/sailboat/1368Sailboat.gltf","scale":1.0,"heightReference":"RELATIVE_TO_GROUND"},"orientation":{"velocityReference":"#position"},"position":{"cartographicDegrees":["2024-07-08T17:08:51Z",0.129617,49.49022,-10,"2024-07-08T17:09:31Z",0.129617,49.49022,-10],"interpolationAlgorithm":"LINEAR","forwardExtrapolationType":"HOLD"}},{"id":"YOYO44840","label":{"text":"YOYO44840","scale":0.3,"pixelOffset":{"cartesian2":[0.0, -40.0]}},"model":{"gltf":"models/sailboat/1368Sailboat.gltf","scale":1.0,"heightReference":"RELATIVE_TO_GROUND"},"orientation":{"velocityReference":"#position"},"position":{"cartographicDegrees":["2024-07-08T17:08:51Z",0.129617,49.49022,-10,"2024-07-08T17:09:31Z",0.129617,49.49022,-10],"interpolationAlgorithm":"LINEAR","forwardExtrapolationType":"HOLD"}},{"id":"MONTIGJE","label":{"text":"MONTIGJE","scale":0.3,"pixelOffset":{"cartesian2":[0.0, -40.0]}},"model":{"gltf":"models/sailboat/1368Sailboat.gltf","scale":1.0,"heightReference":"RELATIVE_TO_GROUND"},"orientation":{"velocityReference":"#position"},"position":{"cartographicDegrees":["2024-07-08T17:08:51Z",0.129617,49.49022,-10,"2024-07-08T17:09:31Z",0.129617,49.49022,-10],"interpolationAlgorithm":"LINEAR","forwardExtrapolationType":"HOLD"}},{"id":"WAYNESWORLD - FLYING","label":{"text":"WAYNESWORLD - FLYING","scale":0.3,"pixelOffset":{"cartesian2":[0.0, -40.0]}},"model":{"gltf":"models/sailboat/1368Sailboat.gltf","scale":1.0,"heightReference":"RELATIVE_TO_GROUND"},"orientation":{"velocityReference":"#position"},"position":{"cartographicDegrees":["2024-07-08T17:08:51Z",0.129617,49.49022,-10,"2024-07-08T17:09:31Z",0.129617,49.49022,-10],"interpolationAlgorithm":"LINEAR","forwardExtrapolationType":"HOLD"}},{"id":"GUS66","label":{"text":"GUS66","scale":0.3,"pixelOffset":{"cartesian2":[0.0, -40.0]}},"model":{"gltf":"models/sailboat/1368Sailboat.gltf","scale":1.0,"heightReference":"RELATIVE_TO_GROUND"},"orientation":{"velocityReference":"#position"},"position":{"cartographicDegrees":["2024-07-08T17:08:51Z",-1.80794408876628,50.5640151030202,-10,"2024-07-08T17:09:31Z",-1.80654485126765,50.5656185724833,-10],"interpolationAlgorithm":"LINEAR","forwardExtrapolationType":"HOLD"}},{"id":"CAFIALIMENTATION CRE","label":{"text":"CAFIALIMENTATION CRE","scale":0.3,"pixelOffset":{"cartesian2":[0.0, -40.0]}},"model":{"gltf":"models/sailboat/1368Sailboat.gltf","scale":1.0,"heightReference":"RELATIVE_TO_GROUND"},"orientation":{"velocityReference":"#position"},"position":{"cartographicDegrees":["2024-07-08T17:08:51Z",0.129617,49.49022,-10,"2024-07-08T17:09:31Z",0.129617,49.49022,-10],"interpolationAlgorithm":"LINEAR","forwardExtrapolationType":"HOLD"}},{"id":"ARMAG","label":{"text":"ARMAG","scale":0.3,"pixelOffset":{"cartesian2":[0.0, -40.0]}},"model":{"gltf":"models/sailboat/1368Sailboat.gltf","scale":1.0,"heightReference":"RELATIVE_TO_GROUND"},"orientation":{"velocityReference":"#position"},"position":{"cartographicDegrees":["2024-07-08T17:08:51Z",0.129617,49.49022,-10,"2024-07-08T17:09:31Z",0.129617,49.49022,-10],"interpolationAlgorithm":"LINEAR","forwardExtrapolationType":"HOLD"}},{"id":"FALCHETTA","label":{"text":"FALCHETTA","scale":0.3,"pixelOffset":{"cartesian2":[0.0, -40.0]}},"model":{"gltf":"models/sailboat/1368Sailboat.gltf","scale":1.0,"heightReference":"RELATIVE_TO_GROUND"},"orientation":{"velocityReference":"#position"},"position":{"cartographicDegrees":["2024-07-08T17:08:51Z",0.129617,49.49022,-10,"2024-07-08T17:09:31Z",0.129617,49.49022,-10],"interpolationAlgorithm":"LINEAR","forwardExtrapolationType":"HOLD"}},{"id":"FSFSASCS","label":{"text":"FSFSASCS","scale":0.3,"pixelOffset":{"cartesian2":[0.0, -40.0]}},"model":{"gltf":"models/sailboat/1368Sailboat.gltf","scale":1.0,"heightReference":"RELATIVE_TO_GROUND"},"orientation":{"velocityReference":"#position"},"position":{"cartographicDegrees":["2024-07-08T17:08:51Z",0.129617,49.49022,-10,"2024-07-08T17:09:31Z",0.129617,49.49022,-10],"interpolationAlgorithm":"LINEAR","forwardExtrapolationType":"HOLD"}},{"id":"NEPTUNEO","label":{"text":"NEPTUNEO","scale":0.3,"pixelOffset":{"cartesian2":[0.0, -40.0]}},"model":{"gltf":"models/sailboat/1368Sailboat.gltf","scale":1.0,"heightReference":"RELATIVE_TO_GROUND"},"orientation":{"velocityReference":"#position"},"position":{"cartographicDegrees":["2024-07-08T17:08:51Z",0.129617,49.49022,-10,"2024-07-08T17:09:31Z",0.129617,49.49022,-10],"interpolationAlgorithm":"LINEAR","forwardExtrapolationType":"HOLD"}},{"id":"KER MARIO","label":{"text":"KER MARIO","scale":0.3,"pixelOffset":{"cartesian2":[0.0, -40.0]}},"model":{"gltf":"models/sailboat/1368Sailboat.gltf","scale":1.0,"heightReference":"RELATIVE_TO_GROUND"},"orientation":{"velocityReference":"#position"},"position":{"cartographicDegrees":["2024-07-08T17:08:51Z",0.129617,49.49022,-10,"2024-07-08T17:09:31Z",0.129617,49.49022,-10],"interpolationAlgorithm":"LINEAR","forwardExtrapolationType":"HOLD"}},{"id":"PATMAN94","label":{"text":"PATMAN94","scale":0.3,"pixelOffset":{"cartesian2":[0.0, -40.0]}},"model":{"gltf":"models/sailboat/1368Sailboat.gltf","scale":1.0,"heightReference":"RELATIVE_TO_GROUND"},"orientation":{"velocityReference":"#position"},"position":{"cartographicDegrees":["2024-07-08T17:08:51Z",0.129617,49.49022,-10,"2024-07-08T17:09:31Z",0.129617,49.49022,-10],"interpolationAlgorithm":"LINEAR","forwardExtrapolationType":"HOLD"}},{"id":"JERMEY","label":{"text":"JERMEY","scale":0.3,"pixelOffset":{"cartesian2":[0.0, -40.0]}},"model":{"gltf":"models/sailboat/1368Sailboat.gltf","scale":1.0,"heightReference":"RELATIVE_TO_GROUND"},"orientation":{"velocityReference":"#position"},"position":{"cartographicDegrees":["2024-07-08T17:08:51Z",0.129617,49.49022,-10,"2024-07-08T17:09:31Z",0.129617,49.49022,-10],"interpolationAlgorithm":"LINEAR","forwardExtrapolationType":"HOLD"}},{"id":"WALTAS-EB","label":{"text":"WALTAS-EB","scale":0.3,"pixelOffset":{"cartesian2":[0.0, -40.0]}},"model":{"gltf":"models/sailboat/1368Sailboat.gltf","scale":1.0,"heightReference":"RELATIVE_TO_GROUND"},"orientation":{"velocityReference":"#position"},"position":{"cartographicDegrees":["2024-07-08T17:08:51Z",0.129617,49.49022,-10,"2024-07-08T17:09:31Z",0.129617,49.49022,-10],"interpolationAlgorithm":"LINEAR","forwardExtrapolationType":"HOLD"}},{"id":"LORDROY","label":{"text":"LORDROY","scale":0.3,"pixelOffset":{"cartesian2":[0.0, -40.0]}},"model":{"gltf":"models/sailboat/1368Sailboat.gltf","scale":1.0,"heightReference":"RELATIVE_TO_GROUND"},"orientation":{"velocityReference":"#position"},"position":{"cartographicDegrees":["2024-07-08T17:08:51Z",0.129617,49.49022,-10,"2024-07-08T17:09:31Z",0.129617,49.49022,-10],"interpolationAlgorithm":"LINEAR","forwardExtrapolationType":"HOLD"}},{"id":"MACEO LE BG","label":{"text":"MACEO LE BG","scale":0.3,"pixelOffset":{"cartesian2":[0.0, -40.0]}},"model":{"gltf":"models/sailboat/1368Sailboat.gltf","scale":1.0,"heightReference":"RELATIVE_TO_GROUND"},"orientation":{"velocityReference":"#position"},"position":{"cartographicDegrees":["2024-07-08T17:08:51Z",-0.654415216887052,49.9919228269218,-10,"2024-07-08T17:09:31Z",-0.655214102337139,49.990752813608,-10],"interpolationAlgorithm":"LINEAR","forwardExtrapolationType":"HOLD"}},{"id":"PSI1370","label":{"text":"PSI1370","scale":0.3,"pixelOffset":{"cartesian2":[0.0, -40.0]}},"model":{"gltf":"models/sailboat/1368Sailboat.gltf","scale":1.0,"heightReference":"RELATIVE_TO_GROUND"},"orientation":{"velocityReference":"#position"},"position":{"cartographicDegrees":["2024-07-08T17:08:51Z",0.129617,49.49022,-10,"2024-07-08T17:09:31Z",0.129617,49.49022,-10],"interpolationAlgorithm":"LINEAR","forwardExtrapolationType":"HOLD"}},{"id":"CATRICOTE - TB5","label":{"text":"CATRICOTE - TB5","scale":0.3,"pixelOffset":{"cartesian2":[0.0, -40.0]}},"model":{"gltf":"models/sailboat/1368Sailboat.gltf","scale":1.0,"heightReference":"RELATIVE_TO_GROUND"},"orientation":{"velocityReference":"#position"},"position":{"cartographicDegrees":["2024-07-08T17:08:51Z",0.129617,49.49022,-10,"2024-07-08T17:09:31Z",0.129617,49.49022,-10],"interpolationAlgorithm":"LINEAR","forwardExtrapolationType":"HOLD"}},{"id":"F561","label":{"text":"F561","scale":0.3,"pixelOffset":{"cartesian2":[0.0, -40.0]}},"model":{"gltf":"models/sailboat/1368Sailboat.gltf","scale":1.0,"heightReference":"RELATIVE_TO_GROUND"},"orientation":{"velocityReference":"#position"},"position":{"cartographicDegrees":["2024-07-08T17:08:51Z",0.129617,49.49022,-10,"2024-07-08T17:09:31Z",0.129617,49.49022,-10],"interpolationAlgorithm":"LINEAR","forwardExtrapolationType":"HOLD"}},{"id":"BREIZH29340","label":{"text":"BREIZH29340","scale":0.3,"pixelOffset":{"cartesian2":[0.0, -40.0]}},"model":{"gltf":"models/sailboat/1368Sailboat.gltf","scale":1.0,"heightReference":"RELATIVE_TO_GROUND"},"orientation":{"velocityReference":"#position"},"position":{"cartographicDegrees":["2024-07-08T17:08:51Z",0.129617,49.49022,-10,"2024-07-08T17:09:31Z",0.129617,49.49022,-10],"interpolationAlgorithm":"LINEAR","forwardExtrapolationType":"HOLD"}},{"id":"DOLIP44","label":{"text":"DOLIP44","scale":0.3,"pixelOffset":{"cartesian2":[0.0, -40.0]}},"model":{"gltf":"models/sailboat/1368Sailboat.gltf","scale":1.0,"heightReference":"RELATIVE_TO_GROUND"},"orientation":{"velocityReference":"#position"},"position":{"cartographicDegrees":["2024-07-08T17:08:51Z",-1.13353244818195,50.7488531080344,-10,"2024-07-08T17:09:31Z",-1.13291921012525,50.7484555009601,-10],"interpolationAlgorithm":"LINEAR","forwardExtrapolationType":"HOLD"}},{"id":"MATU","label":{"text":"MATU","scale":0.3,"pixelOffset":{"cartesian2":[0.0, -40.0]}},"model":{"gltf":"models/sailboat/1368Sailboat.gltf","scale":1.0,"heightReference":"RELATIVE_TO_GROUND"},"orientation":{"velocityReference":"#position"},"position":{"cartographicDegrees":["2024-07-08T17:08:51Z",-1.84770870068832,50.394261979935,-10,"2024-07-08T17:09:31Z",-1.84658780259489,50.3958898245454,-10],"interpolationAlgorithm":"LINEAR","forwardExtrapolationType":"HOLD"}},{"id":"ARDENMARINE","label":{"text":"ARDENMARINE","scale":0.3,"pixelOffset":{"cartesian2":[0.0, -40.0]}},"model":{"gltf":"models/sailboat/1368Sailboat.gltf","scale":1.0,"heightReference":"RELATIVE_TO_GROUND"},"orientation":{"velocityReference":"#position"},"position":{"cartographicDegrees":["2024-07-08T17:08:51Z",0.129617,49.49022,-10,"2024-07-08T17:09:31Z",0.129617,49.49022,-10],"interpolationAlgorithm":"LINEAR","forwardExtrapolationType":"HOLD"}},{"id":"BOSCO44972","label":{"text":"BOSCO44972","scale":0.3,"pixelOffset":{"cartesian2":[0.0, -40.0]}},"model":{"gltf":"models/sailboat/1368Sailboat.gltf","scale":1.0,"heightReference":"RELATIVE_TO_GROUND"},"orientation":{"velocityReference":"#position"},"position":{"cartographicDegrees":["2024-07-08T17:08:51Z",-0.367820541806897,50.5091297040308,-10,"2024-07-08T17:09:31Z",-0.366421820282043,50.5087149120332,-10],"interpolationAlgorithm":"LINEAR","forwardExtrapolationType":"HOLD"}},{"id":"VENT DE DALT","label":{"text":"VENT DE DALT","scale":0.3,"pixelOffset":{"cartesian2":[0.0, -40.0]}},"model":{"gltf":"models/sailboat/1368Sailboat.gltf","scale":1.0,"heightReference":"RELATIVE_TO_GROUND"},"orientation":{"velocityReference":"#position"},"position":{"cartographicDegrees":["2024-07-08T17:08:51Z",0.129617,49.49022,-10,"2024-07-08T17:09:31Z",0.129617,49.49022,-10],"interpolationAlgorithm":"LINEAR","forwardExtrapolationType":"HOLD"}},{"id":"TEOTOM18 .C2B-ESF3","label":{"text":"TEOTOM18 .C2B-ESF3","scale":0.3,"pixelOffset":{"cartesian2":[0.0, -40.0]}},"model":{"gltf":"models/sailboat/1368Sailboat.gltf","scale":1.0,"heightReference":"RELATIVE_TO_GROUND"},"orientation":{"velocityReference":"#position"},"position":{"cartographicDegrees":["2024-07-08T17:08:51Z",0.129617,49.49022,-10,"2024-07-08T17:09:31Z",0.129617,49.49022,-10],"interpolationAlgorithm":"LINEAR","forwardExtrapolationType":"HOLD"}},{"id":"IGREY","label":{"text":"IGREY","scale":0.3,"pixelOffset":{"cartesian2":[0.0, -40.0]}},"model":{"gltf":"models/sailboat/1368Sailboat.gltf","scale":1.0,"heightReference":"RELATIVE_TO_GROUND"},"orientation":{"velocityReference":"#position"},"position":{"cartographicDegrees":["2024-07-08T17:08:51Z",0.129617,49.49022,-10,"2024-07-08T17:09:31Z",0.129617,49.49022,-10],"interpolationAlgorithm":"LINEAR","forwardExtrapolationType":"HOLD"}},{"id":"ZYLOR_DANYLORS","label":{"text":"ZYLOR_DANYLORS","scale":0.3,"pixelOffset":{"cartesian2":[0.0, -40.0]}},"model":{"gltf":"models/sailboat/1368Sailboat.gltf","scale":1.0,"heightReference":"RELATIVE_TO_GROUND"},"orientation":{"velocityReference":"#position"},"position":{"cartographicDegrees":["2024-07-08T17:08:51Z",0.129617,49.49022,-10,"2024-07-08T17:09:31Z",0.129617,49.49022,-10],"interpolationAlgorithm":"LINEAR","forwardExtrapolationType":"HOLD"}},{"id":"MC KELE / INC-BUREAU","label":{"text":"MC KELE / INC-BUREAU","scale":0.3,"pixelOffset":{"cartesian2":[0.0, -40.0]}},"model":{"gltf":"models/sailboat/1368Sailboat.gltf","scale":1.0,"heightReference":"RELATIVE_TO_GROUND"},"orientation":{"velocityReference":"#position"},"position":{"cartographicDegrees":["2024-07-08T17:08:51Z",0.129617,49.49022,-10,"2024-07-08T17:09:31Z",0.129617,49.49022,-10],"interpolationAlgorithm":"LINEAR","forwardExtrapolationType":"HOLD"}},{"id":"HARDIN87 (MC)","label":{"text":"HARDIN87 (MC)","scale":0.3,"pixelOffset":{"cartesian2":[0.0, -40.0]}},"model":{"gltf":"models/sailboat/1368Sailboat.gltf","scale":1.0,"heightReference":"RELATIVE_TO_GROUND"},"orientation":{"velocityReference":"#position"},"position":{"cartographicDegrees":["2024-07-08T17:08:51Z",0.129617,49.49022,-10,"2024-07-08T17:09:31Z",0.129617,49.49022,-10],"interpolationAlgorithm":"LINEAR","forwardExtrapolationType":"HOLD"}},{"id":"PAPIDODO","label":{"text":"PAPIDODO","scale":0.3,"pixelOffset":{"cartesian2":[0.0, -40.0]}},"model":{"gltf":"models/sailboat/1368Sailboat.gltf","scale":1.0,"heightReference":"RELATIVE_TO_GROUND"},"orientation":{"velocityReference":"#position"},"position":{"cartographicDegrees":["2024-07-08T17:08:51Z",-2.2352890489097,50.4739470689372,-10,"2024-07-08T17:09:31Z",-2.23317060457557,50.4744113050093,-10],"interpolationAlgorithm":"LINEAR","forwardExtrapolationType":"HOLD"}},{"id":"NICO_JUD - PVE","label":{"text":"NICO_JUD - PVE","scale":0.3,"pixelOffset":{"cartesian2":[0.0, -40.0]}},"model":{"gltf":"models/sailboat/1368Sailboat.gltf","scale":1.0,"heightReference":"RELATIVE_TO_GROUND"},"orientation":{"velocityReference":"#position"},"position":{"cartographicDegrees":["2024-07-08T17:08:51Z",0.129617,49.49022,-10,"2024-07-08T17:09:31Z",0.129617,49.49022,-10],"interpolationAlgorithm":"LINEAR","forwardExtrapolationType":"HOLD"}},{"id":"AR VAG >^;^","label":{"text":"AR VAG >^;^","scale":0.3,"pixelOffset":{"cartesian2":[0.0, -40.0]}},"model":{"gltf":"models/sailboat/1368Sailboat.gltf","scale":1.0,"heightReference":"RELATIVE_TO_GROUND"},"orientation":{"velocityReference":"#position"},"position":{"cartographicDegrees":["2024-07-08T17:08:51Z",0.129617,49.49022,-10,"2024-07-08T17:09:31Z",0.129617,49.49022,-10],"interpolationAlgorithm":"LINEAR","forwardExtrapolationType":"HOLD"}},{"id":"TEMERUS - PVE","label":{"text":"TEMERUS - PVE","scale":0.3,"pixelOffset":{"cartesian2":[0.0, -40.0]}},"model":{"gltf":"models/sailboat/1368Sailboat.gltf","scale":1.0,"heightReference":"RELATIVE_TO_GROUND"},"orientation":{"velocityReference":"#position"},"position":{"cartographicDegrees":["2024-07-08T17:08:51Z",0.129617,49.49022,-10,"2024-07-08T17:09:31Z",0.129617,49.49022,-10],"interpolationAlgorithm":"LINEAR","forwardExtrapolationType":"HOLD"}},{"id":"MAIWENNREDONEC - LBP","label":{"text":"MAIWENNREDONEC - LBP","scale":0.3,"pixelOffset":{"cartesian2":[0.0, -40.0]}},"model":{"gltf":"models/sailboat/1368Sailboat.gltf","scale":1.0,"heightReference":"RELATIVE_TO_GROUND"},"orientation":{"velocityReference":"#position"},"position":{"cartographicDegrees":["2024-07-08T17:08:51Z",0.129617,49.49022,-10,"2024-07-08T17:09:31Z",0.129617,49.49022,-10],"interpolationAlgorithm":"LINEAR","forwardExtrapolationType":"HOLD"}},{"id":"LEGEND 1 - PSA","label":{"text":"LEGEND 1 - PSA","scale":0.3,"pixelOffset":{"cartesian2":[0.0, -40.0]}},"model":{"gltf":"models/sailboat/1368Sailboat.gltf","scale":1.0,"heightReference":"RELATIVE_TO_GROUND"},"orientation":{"velocityReference":"#position"},"position":{"cartographicDegrees":["2024-07-08T17:08:51Z",0.129617,49.49022,-10,"2024-07-08T17:09:31Z",0.129617,49.49022,-10],"interpolationAlgorithm":"LINEAR","forwardExtrapolationType":"HOLD"}},{"id":"SANDYGND 85_TVD/SODE","label":{"text":"SANDYGND 85_TVD/SODE","scale":0.3,"pixelOffset":{"cartesian2":[0.0, -40.0]}},"model":{"gltf":"models/sailboat/1368Sailboat.gltf","scale":1.0,"heightReference":"RELATIVE_TO_GROUND"},"orientation":{"velocityReference":"#position"},"position":{"cartographicDegrees":["2024-07-08T17:08:51Z",0.129617,49.49022,-10,"2024-07-08T17:09:31Z",0.129617,49.49022,-10],"interpolationAlgorithm":"LINEAR","forwardExtrapolationType":"HOLD"}},{"id":"THEFLYINGCAT ZERO FU","label":{"text":"THEFLYINGCAT ZERO FU","scale":0.3,"pixelOffset":{"cartesian2":[0.0, -40.0]}},"model":{"gltf":"models/sailboat/1368Sailboat.gltf","scale":1.0,"heightReference":"RELATIVE_TO_GROUND"},"orientation":{"velocityReference":"#position"},"position":{"cartographicDegrees":["2024-07-08T17:08:51Z",0.129617,49.49022,-10,"2024-07-08T17:09:31Z",0.129617,49.49022,-10],"interpolationAlgorithm":"LINEAR","forwardExtrapolationType":"HOLD"}},{"id":"SANDOKAN-EZ THESEACL","label":{"text":"SANDOKAN-EZ THESEACL","scale":0.3,"pixelOffset":{"cartesian2":[0.0, -40.0]}},"model":{"gltf":"models/sailboat/1368Sailboat.gltf","scale":1.0,"heightReference":"RELATIVE_TO_GROUND"},"orientation":{"velocityReference":"#position"},"position":{"cartographicDegrees":["2024-07-08T17:08:51Z",0.129617,49.49022,-10,"2024-07-08T17:09:31Z",0.129617,49.49022,-10],"interpolationAlgorithm":"LINEAR","forwardExtrapolationType":"HOLD"}},{"id":"BXMAN8","label":{"text":"BXMAN8","scale":0.3,"pixelOffset":{"cartesian2":[0.0, -40.0]}},"model":{"gltf":"models/sailboat/1368Sailboat.gltf","scale":1.0,"heightReference":"RELATIVE_TO_GROUND"},"orientation":{"velocityReference":"#position"},"position":{"cartographicDegrees":["2024-07-08T17:08:51Z",0.129617,49.49022,-10,"2024-07-08T17:09:31Z",0.129617,49.49022,-10],"interpolationAlgorithm":"LINEAR","forwardExtrapolationType":"HOLD"}},{"id":"BIGOODEN29","label":{"text":"BIGOODEN29","scale":0.3,"pixelOffset":{"cartesian2":[0.0, -40.0]}},"model":{"gltf":"models/sailboat/1368Sailboat.gltf","scale":1.0,"heightReference":"RELATIVE_TO_GROUND"},"orientation":{"velocityReference":"#position"},"position":{"cartographicDegrees":["2024-07-08T17:08:51Z",-0.993413755536662,50.7439544679251,-10,"2024-07-08T17:09:31Z",-0.991474738997375,50.7436711962271,-10],"interpolationAlgorithm":"LINEAR","forwardExtrapolationType":"HOLD"}},{"id":"HARRYBO972","label":{"text":"HARRYBO972","scale":0.3,"pixelOffset":{"cartesian2":[0.0, -40.0]}},"model":{"gltf":"models/sailboat/1368Sailboat.gltf","scale":1.0,"heightReference":"RELATIVE_TO_GROUND"},"orientation":{"velocityReference":"#position"},"position":{"cartographicDegrees":["2024-07-08T17:08:51Z",0.129617,49.49022,-10,"2024-07-08T17:09:31Z",0.129617,49.49022,-10],"interpolationAlgorithm":"LINEAR","forwardExtrapolationType":"HOLD"}},{"id":"ROMYBUS","label":{"text":"ROMYBUS","scale":0.3,"pixelOffset":{"cartesian2":[0.0, -40.0]}},"model":{"gltf":"models/sailboat/1368Sailboat.gltf","scale":1.0,"heightReference":"RELATIVE_TO_GROUND"},"orientation":{"velocityReference":"#position"},"position":{"cartographicDegrees":["2024-07-08T17:08:51Z",0.0611862427020823,49.4968733895365,-10,"2024-07-08T17:09:31Z",0.0619183996146556,49.4967188810393,-10],"interpolationAlgorithm":"LINEAR","forwardExtrapolationType":"HOLD"}},{"id":"RAILZ","label":{"text":"RAILZ","scale":0.3,"pixelOffset":{"cartesian2":[0.0, -40.0]}},"model":{"gltf":"models/sailboat/1368Sailboat.gltf","scale":1.0,"heightReference":"RELATIVE_TO_GROUND"},"orientation":{"velocityReference":"#position"},"position":{"cartographicDegrees":["2024-07-08T17:08:51Z",0.129617,49.49022,-10,"2024-07-08T17:09:31Z",0.129617,49.49022,-10],"interpolationAlgorithm":"LINEAR","forwardExtrapolationType":"HOLD"}},{"id":"CARAMBAR II","label":{"text":"CARAMBAR II","scale":0.3,"pixelOffset":{"cartesian2":[0.0, -40.0]}},"model":{"gltf":"models/sailboat/1368Sailboat.gltf","scale":1.0,"heightReference":"RELATIVE_TO_GROUND"},"orientation":{"velocityReference":"#position"},"position":{"cartographicDegrees":["2024-07-08T17:08:51Z",0.129617,49.49022,-10,"2024-07-08T17:09:31Z",0.129617,49.49022,-10],"interpolationAlgorithm":"LINEAR","forwardExtrapolationType":"HOLD"}},{"id":"STEPH33590","label":{"text":"STEPH33590","scale":0.3,"pixelOffset":{"cartesian2":[0.0, -40.0]}},"model":{"gltf":"models/sailboat/1368Sailboat.gltf","scale":1.0,"heightReference":"RELATIVE_TO_GROUND"},"orientation":{"velocityReference":"#position"},"position":{"cartographicDegrees":["2024-07-08T17:08:51Z",0.129617,49.49022,-10,"2024-07-08T17:09:31Z",0.129617,49.49022,-10],"interpolationAlgorithm":"LINEAR","forwardExtrapolationType":"HOLD"}},{"id":"OEILDELYNX2008 / LSV","label":{"text":"OEILDELYNX2008 / LSV","scale":0.3,"pixelOffset":{"cartesian2":[0.0, -40.0]}},"model":{"gltf":"models/sailboat/1368Sailboat.gltf","scale":1.0,"heightReference":"RELATIVE_TO_GROUND"},"orientation":{"velocityReference":"#position"},"position":{"cartographicDegrees":["2024-07-08T17:08:51Z",0.129617,49.49022,-10,"2024-07-08T17:09:31Z",0.129617,49.49022,-10],"interpolationAlgorithm":"LINEAR","forwardExtrapolationType":"HOLD"}},{"id":"PYF 85","label":{"text":"PYF 85","scale":0.3,"pixelOffset":{"cartesian2":[0.0, -40.0]}},"model":{"gltf":"models/sailboat/1368Sailboat.gltf","scale":1.0,"heightReference":"RELATIVE_TO_GROUND"},"orientation":{"velocityReference":"#position"},"position":{"cartographicDegrees":["2024-07-08T17:08:51Z",-0.0894910622949736,50.2299342353828,-10,"2024-07-08T17:09:31Z",-0.0907192381643777,50.2291485611815,-10],"interpolationAlgorithm":"LINEAR","forwardExtrapolationType":"HOLD"}},{"id":"MYKIDSAREMARTIANS_PO","label":{"text":"MYKIDSAREMARTIANS_PO","scale":0.3,"pixelOffset":{"cartesian2":[0.0, -40.0]}},"model":{"gltf":"models/sailboat/1368Sailboat.gltf","scale":1.0,"heightReference":"RELATIVE_TO_GROUND"},"orientation":{"velocityReference":"#position"},"position":{"cartographicDegrees":["2024-07-08T17:08:51Z",0.129617,49.49022,-10,"2024-07-08T17:09:31Z",0.129617,49.49022,-10],"interpolationAlgorithm":"LINEAR","forwardExtrapolationType":"HOLD"}},{"id":"LA CIGOGNE 44 GLP","label":{"text":"LA CIGOGNE 44 GLP","scale":0.3,"pixelOffset":{"cartesian2":[0.0, -40.0]}},"model":{"gltf":"models/sailboat/1368Sailboat.gltf","scale":1.0,"heightReference":"RELATIVE_TO_GROUND"},"orientation":{"velocityReference":"#position"},"position":{"cartographicDegrees":["2024-07-08T17:08:51Z",-0.435395105274871,50.5943007858375,-10,"2024-07-08T17:09:31Z",-0.433399191780831,50.5940268462865,-10],"interpolationAlgorithm":"LINEAR","forwardExtrapolationType":"HOLD"}},{"id":"TIPAPACHERI BSP","label":{"text":"TIPAPACHERI BSP","scale":0.3,"pixelOffset":{"cartesian2":[0.0, -40.0]}},"model":{"gltf":"models/sailboat/1368Sailboat.gltf","scale":1.0,"heightReference":"RELATIVE_TO_GROUND"},"orientation":{"velocityReference":"#position"},"position":{"cartographicDegrees":["2024-07-08T17:08:51Z",0.129617,49.49022,-10,"2024-07-08T17:09:31Z",0.129617,49.49022,-10],"interpolationAlgorithm":"LINEAR","forwardExtrapolationType":"HOLD"}},{"id":"russor","label":{"text":"russor","scale":0.3,"pixelOffset":{"cartesian2":[0.0, -40.0]}},"model":{"gltf":"models/sailboat/1368Sailboat.gltf","scale":1.0,"heightReference":"RELATIVE_TO_GROUND"},"orientation":{"velocityReference":"#position"},"position":{"cartographicDegrees":["2024-07-08T17:08:51Z",-0.505425826870603,49.9399947790024,-10,"2024-07-08T17:09:31Z",-0.504714868404941,49.9388909363615,-10],"interpolationAlgorithm":"LINEAR","forwardExtrapolationType":"HOLD"}}]